{
  "run_id": "MMPO2-L4-d8-seed7",
  "seed": 7,
  "model": "MMPO2",
  "dataset": "bike",
  "task": "regression",
  "params": {
    "output_site": 1,
    "init_strength": 0.01,
    "rank": 5,
    "batch_size": 64,
    "n_epochs": 1000,
    "patience": 40,
    "min_delta": 1e-08,
    "optimizer": "adamw",
    "seeds": [
      42,
      7,
      123,
      256,
      999
    ],
    "model": "MMPO2",
    "L": 4,
    "bond_dim": 8,
    "lr": 0.01
  },
  "n_parameters": 1728,
  "train_loss": 13038.166625164313,
  "train_quality": 0.6102192434637341,
  "val_loss": 13581.336118348012,
  "val_quality": 0.5946492106874264,
  "test_loss": 12684.570225790718,
  "test_quality": 0.5882211487513153,
  "best_epoch": 113,
  "stopped_early": true,
  "patience_counter": 40,
  "success": true
}