{
  "run_id": "LMPO2-L3-d12-rf0.5-seed999",
  "seed": 999,
  "model": "LMPO2",
  "dataset": "appliances",
  "task": "regression",
  "params": {
    "output_site": 1,
    "init_strength": 0.01,
    "reduction_factor": 0.5,
    "rank": 5,
    "batch_size": 64,
    "n_epochs": 1000,
    "patience": 40,
    "min_delta": 1e-08,
    "optimizer": "adamw",
    "seeds": [
      42,
      7,
      123,
      256,
      999
    ],
    "model": "LMPO2",
    "L": 3,
    "bond_dim": 12,
    "lr": 0.01
  },
  "n_parameters": 23520,
  "train_loss": 6465.379785249639,
  "train_quality": 0.3900617243995449,
  "val_loss": 7249.524011171696,
  "val_quality": 0.1931751454387356,
  "test_loss": 9012.776111892876,
  "test_quality": 0.25008466113431727,
  "best_epoch": 148,
  "stopped_early": true,
  "patience_counter": 40,
  "success": true
}