{
  "run_id": "MPO2-L4-d12-seed123",
  "seed": 123,
  "model": "MPO2",
  "dataset": "student_perf",
  "task": "regression",
  "params": {
    "output_site": 1,
    "init_strength": 0.01,
    "batch_size": 64,
    "n_epochs": 1000,
    "patience": 40,
    "min_delta": 1e-08,
    "optimizer": "adamw",
    "rank": 5,
    "seeds": [
      42,
      7,
      123,
      256,
      999
    ],
    "model": "MPO2",
    "L": 4,
    "bond_dim": 12,
    "lr": 0.01
  },
  "n_parameters": 15600,
  "train_loss": 0.02992211949415022,
  "train_quality": 0.9957829324320022,
  "val_loss": 98.51632429095581,
  "val_quality": -14.457245451801013,
  "test_loss": 213.98278209122117,
  "test_quality": -20.142907810741647,
  "best_epoch": 999,
  "stopped_early": false,
  "patience_counter": 0,
  "success": true
}