{
  "config": {
    "experiment_name": "gtn_student_perf",
    "dataset": "student_perf",
    "task": "regression",
    "parameter_grid": {
      "model": [
        "MPO2",
        "MPO2TypeI_GTN",
        "MMPO2",
        "MMPO2TypeI_GTN"
      ],
      "L": [
        3,
        4
      ],
      "bond_dim": [
        8,
        12,
        16
      ],
      "lr": [
        0.01,
        0.001,
        0.0001
      ]
    },
    "fixed_params": {
      "output_site": 1,
      "batch_size": 64,
      "n_epochs": 1000,
      "patience": 40,
      "min_delta": 1e-08,
      "optimizer": "adamw",
      "init_strength": 0.01,
      "rank": 5,
      "seeds": [
        42,
        7,
        123,
        256,
        999
      ]
    },
    "tracker": {
      "backend": "both",
      "tracker_dir": "experiment_logs",
      "aim_repo": "aim://aimtracking.kosmon.org:443"
    },
    "output": {
      "results_dir": "results/gtn_student_perf",
      "save_models": false,
      "save_individual_runs": true
    }
  },
  "dataset_info": {
    "name": "student_perf",
    "dataset_id": 320,
    "n_samples": 649,
    "n_train": 454,
    "n_val": 97,
    "n_test": 98,
    "n_features": 50,
    "task": "regression"
  },
  "total_runs": 360,
  "completed": 30,
  "skipped": 240,
  "failed": 90,
  "elapsed_time": 4145.164644002914,
  "top_configurations": [
    {
      "run_id": "MMPO2-L4-d8-seed7",
      "seed": 7,
      "model": "MMPO2",
      "dataset": "student_perf",
      "task": "regression",
      "params": {
        "output_site": 1,
        "init_strength": 0.01,
        "rank": 5,
        "batch_size": 64,
        "n_epochs": 1000,
        "patience": 40,
        "min_delta": 1e-08,
        "optimizer": "adamw",
        "seeds": [
          42,
          7,
          123,
          256,
          999
        ],
        "model": "MMPO2",
        "L": 4,
        "bond_dim": 8,
        "lr": 0.01
      },
      "n_parameters": 7200,
      "train_loss": 0.04808983676101182,
      "train_quality": 0.9932224690502015,
      "val_loss": 33.208370450139334,
      "val_quality": -4.206356259380089,
      "test_loss": 27.696556472171842,
      "test_quality": -1.7366021436084194,
      "best_epoch": 569,
      "stopped_early": true,
      "patience_counter": 40,
      "success": true
    },
    {
      "run_id": "MMPO2-L4-d8-seed999",
      "seed": 999,
      "model": "MMPO2",
      "dataset": "student_perf",
      "task": "regression",
      "params": {
        "output_site": 1,
        "init_strength": 0.01,
        "rank": 5,
        "batch_size": 64,
        "n_epochs": 1000,
        "patience": 40,
        "min_delta": 1e-08,
        "optimizer": "adamw",
        "seeds": [
          42,
          7,
          123,
          256,
          999
        ],
        "model": "MMPO2",
        "L": 4,
        "bond_dim": 8,
        "lr": 0.01
      },
      "n_parameters": 7200,
      "train_loss": 0.1701205206778391,
      "train_quality": 0.9760241004805268,
      "val_loss": 16.242765730973737,
      "val_quality": -1.4614064431222928,
      "test_loss": 30.937199341593256,
      "test_quality": -2.056798996673473,
      "best_epoch": 767,
      "stopped_early": true,
      "patience_counter": 40,
      "success": true
    },
    {
      "run_id": "MMPO2-L4-d16-seed123",
      "seed": 123,
      "model": "MMPO2",
      "dataset": "student_perf",
      "task": "regression",
      "params": {
        "output_site": 1,
        "init_strength": 0.01,
        "rank": 5,
        "batch_size": 64,
        "n_epochs": 1000,
        "patience": 40,
        "min_delta": 1e-08,
        "optimizer": "adamw",
        "seeds": [
          42,
          7,
          123,
          256,
          999
        ],
        "model": "MMPO2",
        "L": 4,
        "bond_dim": 16,
        "lr": 0.01
      },
      "n_parameters": 27200,
      "train_loss": 0.01658392254846335,
      "train_quality": 0.9976627483911029,
      "val_loss": 54.37411048652332,
      "val_quality": -7.531316795085678,
      "test_loss": 36.65970475811465,
      "test_quality": -2.6222202108737966,
      "best_epoch": 351,
      "stopped_early": true,
      "patience_counter": 40,
      "success": true
    },
    {
      "run_id": "MMPO2-L4-d12-seed999",
      "seed": 999,
      "model": "MMPO2",
      "dataset": "student_perf",
      "task": "regression",
      "params": {
        "output_site": 1,
        "init_strength": 0.01,
        "rank": 5,
        "batch_size": 64,
        "n_epochs": 1000,
        "patience": 40,
        "min_delta": 1e-08,
        "optimizer": "adamw",
        "seeds": [
          42,
          7,
          123,
          256,
          999
        ],
        "model": "MMPO2",
        "L": 4,
        "bond_dim": 12,
        "lr": 0.01
      },
      "n_parameters": 15600,
      "train_loss": 0.0365736609468775,
      "train_quality": 0.9948454988473602,
      "val_loss": 49.24145277823754,
      "val_quality": -6.72600102038482,
      "test_loss": 48.37077779526004,
      "test_quality": -3.779351336889686,
      "best_epoch": 418,
      "stopped_early": true,
      "patience_counter": 40,
      "success": true
    },
    {
      "run_id": "MMPO2-L4-d12-seed123",
      "seed": 123,
      "model": "MMPO2",
      "dataset": "student_perf",
      "task": "regression",
      "params": {
        "output_site": 1,
        "init_strength": 0.01,
        "rank": 5,
        "batch_size": 64,
        "n_epochs": 1000,
        "patience": 40,
        "min_delta": 1e-08,
        "optimizer": "adamw",
        "seeds": [
          42,
          7,
          123,
          256,
          999
        ],
        "model": "MMPO2",
        "L": 4,
        "bond_dim": 12,
        "lr": 0.01
      },
      "n_parameters": 15600,
      "train_loss": 0.02281659923215606,
      "train_quality": 0.9967843474238935,
      "val_loss": 39.82076430329862,
      "val_quality": -5.247891731085523,
      "test_loss": 67.28715933232183,
      "test_quality": -5.648414385057807,
      "best_epoch": 369,
      "stopped_early": true,
      "patience_counter": 40,
      "success": true
    },
    {
      "run_id": "MMPO2-L3-d8-seed42",
      "seed": 42,
      "model": "MMPO2",
      "dataset": "student_perf",
      "task": "regression",
      "params": {
        "output_site": 1,
        "init_strength": 0.01,
        "rank": 5,
        "batch_size": 64,
        "n_epochs": 1000,
        "patience": 40,
        "min_delta": 1e-08,
        "optimizer": "adamw",
        "seeds": [
          42,
          7,
          123,
          256,
          999
        ],
        "model": "MMPO2",
        "L": 3,
        "bond_dim": 8,
        "lr": 0.01
      },
      "n_parameters": 4000,
      "train_loss": 0.39016711647904534,
      "train_quality": 0.9450118801469034,
      "val_loss": 65.23520339205652,
      "val_quality": -9.235426039151875,
      "test_loss": 114.25486448584459,
      "test_quality": -10.289132906605468,
      "best_epoch": 310,
      "stopped_early": true,
      "patience_counter": 40,
      "success": true
    },
    {
      "run_id": "MMPO2-L4-d16-seed42",
      "seed": 42,
      "model": "MMPO2",
      "dataset": "student_perf",
      "task": "regression",
      "params": {
        "output_site": 1,
        "init_strength": 0.01,
        "rank": 5,
        "batch_size": 64,
        "n_epochs": 1000,
        "patience": 40,
        "min_delta": 1e-08,
        "optimizer": "adamw",
        "seeds": [
          42,
          7,
          123,
          256,
          999
        ],
        "model": "MMPO2",
        "L": 4,
        "bond_dim": 16,
        "lr": 0.01
      },
      "n_parameters": 27200,
      "train_loss": 0.1061906489176757,
      "train_quality": 0.9850340434051498,
      "val_loss": 72.96807540177996,
      "val_quality": -10.448716339636933,
      "test_loss": 120.5994499743366,
      "test_quality": -10.916019727916964,
      "best_epoch": 299,
      "stopped_early": true,
      "patience_counter": 40,
      "success": true
    },
    {
      "run_id": "MMPO2-L3-d8-seed123",
      "seed": 123,
      "model": "MMPO2",
      "dataset": "student_perf",
      "task": "regression",
      "params": {
        "output_site": 1,
        "init_strength": 0.01,
        "rank": 5,
        "batch_size": 64,
        "n_epochs": 1000,
        "patience": 40,
        "min_delta": 1e-08,
        "optimizer": "adamw",
        "seeds": [
          42,
          7,
          123,
          256,
          999
        ],
        "model": "MMPO2",
        "L": 3,
        "bond_dim": 8,
        "lr": 0.01
      },
      "n_parameters": 4000,
      "train_loss": 0.27279645398857777,
      "train_quality": 0.9615534895846886,
      "val_loss": 168.8750695197667,
      "val_quality": -25.274841721034825,
      "test_loss": 130.79769744638216,
      "test_quality": -11.92367372710961,
      "best_epoch": 187,
      "stopped_early": true,
      "patience_counter": 40,
      "success": true
    },
    {
      "run_id": "MMPO2-L4-d8-seed123",
      "seed": 123,
      "model": "MMPO2",
      "dataset": "student_perf",
      "task": "regression",
      "params": {
        "output_site": 1,
        "init_strength": 0.01,
        "rank": 5,
        "batch_size": 64,
        "n_epochs": 1000,
        "patience": 40,
        "min_delta": 1e-08,
        "optimizer": "adamw",
        "seeds": [
          42,
          7,
          123,
          256,
          999
        ],
        "model": "MMPO2",
        "L": 4,
        "bond_dim": 8,
        "lr": 0.01
      },
      "n_parameters": 7200,
      "train_loss": 1.6188721051956316,
      "train_quality": 0.7718446030238095,
      "val_loss": 153.50609626889172,
      "val_quality": -21.54223096220033,
      "test_loss": 145.49761052110912,
      "test_quality": -13.376121928443744,
      "best_epoch": 102,
      "stopped_early": true,
      "patience_counter": 40,
      "success": true
    },
    {
      "run_id": "MMPO2-L4-d12-seed7",
      "seed": 7,
      "model": "MMPO2",
      "dataset": "student_perf",
      "task": "regression",
      "params": {
        "output_site": 1,
        "init_strength": 0.01,
        "rank": 5,
        "batch_size": 64,
        "n_epochs": 1000,
        "patience": 40,
        "min_delta": 1e-08,
        "optimizer": "adamw",
        "seeds": [
          42,
          7,
          123,
          256,
          999
        ],
        "model": "MMPO2",
        "L": 4,
        "bond_dim": 12,
        "lr": 0.01
      },
      "n_parameters": 15600,
      "train_loss": 0.026863719297109828,
      "train_quality": 0.9962139674154504,
      "val_loss": 53.21507061254189,
      "val_quality": -7.349463036843094,
      "test_loss": 147.50191904567143,
      "test_quality": -13.574160807763668,
      "best_epoch": 322,
      "stopped_early": true,
      "patience_counter": 40,
      "success": true
    }
  ]
}