{
  "run_id": "LMPO2TypeI_GTN-L4-d8-rf0.5-seed42",
  "seed": 42,
  "model": "LMPO2TypeI_GTN",
  "dataset": "wine",
  "task": "classification",
  "params": {
    "init_strength": 0.01,
    "batch_size": 64,
    "n_epochs": 1000,
    "patience": 40,
    "min_delta": 1e-08,
    "optimizer": "adamw",
    "bond_dim_mpo": 2,
    "seeds": [
      42,
      7,
      123,
      256,
      999
    ],
    "model": "LMPO2TypeI_GTN",
    "L": 4,
    "bond_dim": 8,
    "lr": 0.001,
    "reduction_factor": 0.5
  },
  "n_parameters": 20544,
  "train_loss": 3.57366452009554e-06,
  "train_quality": 1.0,
  "val_loss": 0.043333641192570244,
  "val_quality": 1.0,
  "test_loss": 5.641480721058856e-06,
  "test_quality": 1.0,
  "best_epoch": 32,
  "stopped_early": false,
  "patience_counter": 0,
  "success": true
}