{
  "experiment_name": "debug_batch",
  "dataset": "concrete",
  "task": "regression",
  "parameter_grid": {
    "model": ["MPO2"],
    "L": [3],
    "bond_dim": [4],
    "jitter_start": [1.0]
  },
  "fixed_params": {
    "batch_size": 32,
    "n_epochs": 2,
    "jitter_decay": 0.5,
    "adaptive_jitter": false,
    "patience": 10,
    "min_delta": 1e-5,
    "train_selection": false,
    "init_strength": 0.01,
    "seeds": [42]
  },
  "output": {
    "results_dir": "results/debug_batch",
    "save_individual_runs": true
  },
  "tracker": {
    "backend": "none"
  }
}
