{
  "run_id": "LMPO2TypeI_GTN-L3-d16-rf0.3-seed256",
  "seed": 256,
  "model": "LMPO2TypeI_GTN",
  "dataset": "seoulBike",
  "task": "regression",
  "params": {
    "init_strength": 0.01,
    "batch_size": 64,
    "n_epochs": 1000,
    "patience": 40,
    "min_delta": 1e-08,
    "optimizer": "adamw",
    "bond_dim_mpo": 2,
    "seeds": [
      42,
      7,
      123,
      256,
      999
    ],
    "model": "LMPO2TypeI_GTN",
    "L": 3,
    "bond_dim": 16,
    "lr": 0.001,
    "reduction_factor": 0.3
  },
  "n_parameters": 28890,
  "train_loss": 112440.07126683666,
  "train_quality": 0.7313971147989053,
  "val_loss": 320931.3180639543,
  "val_quality": 0.6947837574875131,
  "test_loss": 126608.96637872393,
  "test_quality": 0.6870531694203411,
  "best_epoch": 155,
  "stopped_early": true,
  "patience_counter": 40,
  "success": true
}