{
  "run_id": "CMPO2_GTN-np14-ns4-rp64-rpa64-init0.01-lr1em03-wd1em02-seed42",
  "seed": 42,
  "model": "CMPO2_GTN",
  "dataset": "MNIST",
  "task": "classification",
  "params": {
    "batch_size": 64,
    "n_epochs": 1000,
    "patience": 30,
    "min_delta": 1e-08,
    "optimizer": "adamw",
    "seeds": [
      42,
      7,
      123
    ],
    "n_patches": 14,
    "n_sites": 4,
    "rank_pixel": 64,
    "rank_patch": 64,
    "lr": 0.001,
    "weight_decay": 0.01,
    "init_strength": 0.01
  },
  "n_parameters": 590464,
  "train_loss": 0.030718720492182487,
  "train_accuracy": 0.9933725490196078,
  "val_loss": 0.2669493572535434,
  "val_accuracy": 0.9787777777777777,
  "test_loss": 0.2612391889129879,
  "test_accuracy": 0.9756,
  "best_epoch": 51,
  "stopped_early": true,
  "patience_counter": 30,
  "success": true
}