{
  "run_id": "LMPO2TypeI_GTN-L4-d8-rf0.1-seed123",
  "seed": 123,
  "model": "LMPO2TypeI_GTN",
  "dataset": "adult",
  "task": "classification",
  "params": {
    "init_strength": 0.01,
    "batch_size": 64,
    "n_epochs": 1000,
    "patience": 40,
    "min_delta": 1e-08,
    "optimizer": "adamw",
    "bond_dim_mpo": 2,
    "seeds": [
      42,
      7,
      123,
      256,
      999
    ],
    "model": "LMPO2TypeI_GTN",
    "L": 4,
    "bond_dim": 8,
    "lr": 0.001,
    "reduction_factor": 0.1
  },
  "n_parameters": 46572,
  "train_loss": 0.8214564598788311,
  "train_quality": 0.6251425897218403,
  "val_loss": 1.2242710836499082,
  "val_quality": 0.5642915642915642,
  "test_loss": 1.2137676602790748,
  "test_quality": 0.5408762112733725,
  "best_epoch": 5,
  "stopped_early": true,
  "patience_counter": 40,
  "success": true
}