{
  "run_id": "MPO2-L3-d16-seed256",
  "seed": 256,
  "model": "MPO2",
  "dataset": "bank",
  "task": "classification",
  "params": {
    "output_site": 1,
    "init_strength": 0.01,
    "batch_size": 64,
    "n_epochs": 1000,
    "patience": 40,
    "min_delta": 1e-08,
    "optimizer": "adamw",
    "rank": 5,
    "seeds": [
      42,
      7,
      123,
      256,
      999
    ],
    "model": "MPO2",
    "L": 3,
    "bond_dim": 16,
    "lr": 0.01
  },
  "n_parameters": 17952,
  "train_loss": 0.6545246489494667,
  "train_quality": 0.8883938445982241,
  "val_loss": 2.515834678185934,
  "val_quality": 0.8908876437629017,
  "test_loss": 0.7766907254660569,
  "test_quality": 0.8807136537894427,
  "best_epoch": 76,
  "stopped_early": true,
  "patience_counter": 40,
  "success": true
}