{
  "experiment_name": "breast",
  "run_name": "MPO2_L2_d4_j1_s7",
  "config": {
    "output_site": 1,
    "init_strength": 0.01,
    "batch_size": 100,
    "n_epochs": 10,
    "jitter_decay": 0.95,
    "jitter_min": 0.001,
    "adaptive_jitter": true,
    "patience": 4,
    "min_delta": 0.001,
    "train_selection": true,
    "rank": 5,
    "seeds": [
      42,
      7,
      123,
      256,
      999
    ],
    "model": "MPO2",
    "L": 2,
    "bond_dim": 4,
    "jitter_start": 1.0,
    "reduction_factor": 0.5
  },
  "hparams": {
    "seed": 7,
    "model": "MPO2",
    "dataset": "breast",
    "output_site": 1,
    "init_strength": 0.01,
    "batch_size": 100,
    "n_epochs": 10,
    "jitter_decay": 0.95,
    "jitter_min": 0.001,
    "adaptive_jitter": true,
    "patience": 4,
    "min_delta": 0.001,
    "train_selection": true,
    "rank": 5,
    "seeds": [
      42,
      7,
      123,
      256,
      999
    ],
    "L": 2,
    "bond_dim": 4,
    "jitter_start": 1.0,
    "reduction_factor": 0.5
  },
  "metrics_log": [
    {
      "step": -1,
      "train_loss": 24.308854278983027,
      "train_quality": 0.3944723618090452,
      "val_loss": 19.614183495688046,
      "val_quality": 0.5058823529411764
    },
    {
      "step": 0,
      "train_loss": 717085.8120047089,
      "train_quality": 0.40703517587939697,
      "val_loss": 581363.4028021434,
      "val_quality": 0.4588235294117647,
      "reg_loss": 27194810144.047264,
      "jitter": 1.0,
      "weight_norm_sq": 27194093058.23526
    },
    {
      "step": 1,
      "train_loss": NaN,
      "train_quality": 0.37939698492462315,
      "val_loss": NaN,
      "val_quality": 0.43529411764705883,
      "reg_loss": NaN,
      "jitter": 0.95,
      "weight_norm_sq": Infinity
    }
  ],
  "summary": {
    "run_id": "MPO2-L2-d4-init0.01-jit1-rf0.5-seed7",
    "seed": 7,
    "model": "MPO2",
    "grid_params": {
      "model": "MPO2",
      "L": 2,
      "bond_dim": 4,
      "jitter_start": 1.0,
      "reduction_factor": 0.5,
      "init_strength": 0.01
    },
    "train_loss": 24.308854278983027,
    "train_quality": 0.3944723618090452,
    "val_loss": 19.614183495688046,
    "val_quality": 0.5058823529411764,
    "test_loss": 30.017964392444366,
    "test_quality": 0.313953488372093,
    "success": true
  }
}