{
  "experiment_name": "breast",
  "run_name": "MPO2_L2_d4_j5_s999",
  "config": {
    "output_site": 1,
    "init_strength": 0.01,
    "batch_size": 100,
    "n_epochs": 10,
    "jitter_decay": 0.95,
    "jitter_min": 0.001,
    "adaptive_jitter": true,
    "patience": 4,
    "min_delta": 0.001,
    "train_selection": true,
    "rank": 5,
    "seeds": [
      42,
      7,
      123,
      256,
      999
    ],
    "model": "MPO2",
    "L": 2,
    "bond_dim": 4,
    "jitter_start": 5.0,
    "reduction_factor": 0.5
  },
  "hparams": {
    "seed": 999,
    "model": "MPO2",
    "dataset": "breast",
    "output_site": 1,
    "init_strength": 0.01,
    "batch_size": 100,
    "n_epochs": 10,
    "jitter_decay": 0.95,
    "jitter_min": 0.001,
    "adaptive_jitter": true,
    "patience": 4,
    "min_delta": 0.001,
    "train_selection": true,
    "rank": 5,
    "seeds": [
      42,
      7,
      123,
      256,
      999
    ],
    "L": 2,
    "bond_dim": 4,
    "jitter_start": 5.0,
    "reduction_factor": 0.5
  },
  "metrics_log": [
    {
      "step": -1,
      "train_loss": 14.42506286776211,
      "train_quality": 0.6080402010050251,
      "val_loss": 19.1883211160195,
      "val_quality": 0.4823529411764706
    },
    {
      "step": 0,
      "train_loss": 208.74796236691594,
      "train_quality": 0.6155778894472362,
      "val_loss": 312.0571727124287,
      "val_quality": 0.6,
      "reg_loss": 11712.618351200228,
      "jitter": 5.0,
      "weight_norm_sq": 2300.7740777666627
    },
    {
      "step": 1,
      "train_loss": 26107367.60843331,
      "train_quality": 0.6180904522613065,
      "val_loss": 43474077.13692305,
      "val_quality": 0.5764705882352941,
      "reg_loss": 58194730919455.28,
      "jitter": 4.75,
      "weight_norm_sq": 12251516802544.773
    },
    {
      "step": 2,
      "train_loss": 279956191121.77747,
      "train_quality": 0.6130653266331658,
      "val_loss": 462236209687.8827,
      "val_quality": 0.5647058823529412,
      "reg_loss": 3.230495508608652e+21,
      "jitter": 4.5125,
      "weight_norm_sq": 7.158992816240877e+20
    },
    {
      "step": 3,
      "train_loss": 70474830434910.92,
      "train_quality": 0.6030150753768845,
      "val_loss": 114355751958965.36,
      "val_quality": 0.5764705882352941,
      "reg_loss": 1.7360755869967763e+26,
      "jitter": 4.286874999999999,
      "weight_norm_sq": 4.049746230053528e+25
    },
    {
      "step": 4,
      "train_loss": 2.1815909731917572e+16,
      "train_quality": 0.6105527638190955,
      "val_loss": 3.5210216535839612e+16,
      "val_quality": 0.5764705882352941,
      "reg_loss": 1.5535924361725381e+31,
      "jitter": 4.072531249999999,
      "weight_norm_sq": 3.8148078941629635e+30
    }
  ],
  "summary": {
    "run_id": "MPO2-L2-d4-init0.01-jit5-rf0.5-seed999",
    "seed": 999,
    "model": "MPO2",
    "grid_params": {
      "model": "MPO2",
      "L": 2,
      "bond_dim": 4,
      "jitter_start": 5.0,
      "reduction_factor": 0.5,
      "init_strength": 0.01
    },
    "train_loss": 208.74796236691594,
    "train_quality": 0.6155778894472362,
    "val_loss": 312.0571727124287,
    "val_quality": 0.6,
    "test_loss": 182.28290360228328,
    "test_quality": 0.6162790697674418,
    "success": true
  }
}