{
  "experiment_name": "ntn_iris",
  "run_name": "MPO2_L4_d16_j5_s999",
  "config": {
    "init_strength": 0.01,
    "batch_size": 1024,
    "n_epochs": 15,
    "jitter_decay": 0.25,
    "adaptive_jitter": false,
    "patience": 4,
    "min_delta": 1e-06,
    "train_selection": true,
    "seeds": [
      42,
      7,
      123,
      256,
      999
    ],
    "model": "MPO2",
    "L": 4,
    "bond_dim": 16,
    "jitter_start": 5.0
  },
  "hparams": {
    "seed": 999,
    "model": "MPO2",
    "dataset": "iris",
    "n_parameters": 2304,
    "init_strength": 0.01,
    "batch_size": 1024,
    "n_epochs": 15,
    "jitter_decay": 0.25,
    "adaptive_jitter": false,
    "patience": 4,
    "min_delta": 1e-06,
    "train_selection": true,
    "seeds": [
      42,
      7,
      123,
      256,
      999
    ],
    "L": 4,
    "bond_dim": 16,
    "jitter_start": 5.0
  },
  "metrics_log": [
    {
      "step": -1,
      "train_loss": 19.222126955025814,
      "train_quality": 0.31428571428571433,
      "val_loss": 25.01199412720347,
      "val_quality": 0.4545454545454546
    },
    {
      "step": 0,
      "train_loss": 5.090133820118367e+162,
      "train_quality": 0.29523809523809524,
      "val_loss": 6.684740485346899e+162,
      "val_quality": 0.5909090909090909,
      "reg_loss": Infinity,
      "jitter": 5.0,
      "weight_norm_sq": Infinity
    }
  ],
  "summary": {
    "run_id": "MPO2-L4-d16-jit5-seed999",
    "seed": 999,
    "model": "MPO2",
    "grid_params": {
      "model": "MPO2",
      "L": 4,
      "bond_dim": 16,
      "jitter_start": 5.0
    },
    "n_parameters": 2304,
    "train_loss": null,
    "train_quality": null,
    "val_loss": null,
    "val_quality": null,
    "test_loss": 4.553191339191553e+162,
    "test_quality": 0.2608695652173913,
    "success": true,
    "singular": true,
    "singular_epoch": 2
  }
}