{
  "experiment_name": "ntn_ai4i",
  "run_name": "MPO2_L2_d4_j0.1_s7",
  "config": {
    "output_site": 1,
    "init_strength": 0.01,
    "batch_size": 100,
    "n_epochs": 10,
    "jitter_decay": 0.25,
    "adaptive_jitter": false,
    "patience": 4,
    "min_delta": 0.0001,
    "train_selection": true,
    "rank": 5,
    "seeds": [
      42,
      7,
      123,
      256,
      999
    ],
    "model": "MPO2",
    "L": 2,
    "bond_dim": 4,
    "jitter_start": 0.1,
    "reduction_factor": 0.5
  },
  "hparams": {
    "seed": 7,
    "model": "MPO2",
    "dataset": "ai4i",
    "output_site": 1,
    "init_strength": 0.01,
    "batch_size": 100,
    "n_epochs": 10,
    "jitter_decay": 0.25,
    "adaptive_jitter": false,
    "patience": 4,
    "min_delta": 0.0001,
    "train_selection": true,
    "rank": 5,
    "seeds": [
      42,
      7,
      123,
      256,
      999
    ],
    "L": 2,
    "bond_dim": 4,
    "jitter_start": 0.1,
    "reduction_factor": 0.5
  },
  "metrics_log": [
    {
      "step": -1,
      "train_loss": 922.2184821767456,
      "train_quality": -27196.797647561176,
      "val_loss": 915.2170252378348,
      "val_quality": -28402.286990139703
    },
    {
      "step": 0,
      "train_loss": 0.026169647503451462,
      "train_quality": 0.22821241271711223,
      "val_loss": 0.024561282712807914,
      "val_quality": 0.2377532951197544,
      "reg_loss": 0.026905717289047552,
      "jitter": 0.1,
      "weight_norm_sq": 0.007360697855960923
    },
    {
      "step": 1,
      "train_loss": 0.02435645423001332,
      "train_quality": 0.2816865782212452,
      "val_loss": 0.022590879520887744,
      "val_quality": 0.2989037390069321,
      "reg_loss": 0.025188513427792793,
      "jitter": 0.025,
      "weight_norm_sq": 0.03328236791117886
    },
    {
      "step": 2,
      "train_loss": 0.023697288442493688,
      "train_quality": 0.3011265027636796,
      "val_loss": 0.02206206180661953,
      "val_quality": 0.31531532324284217,
      "reg_loss": 0.02416974811106978,
      "jitter": 0.00625,
      "weight_norm_sq": 0.07559354697217484
    },
    {
      "step": 3,
      "train_loss": 0.02355362792104435,
      "train_quality": 0.305363296829116,
      "val_loss": 0.021986093353285524,
      "val_quality": 0.3176729648980354,
      "reg_loss": 0.02370885300251815,
      "jitter": 0.0015625,
      "weight_norm_sq": 0.09934405214323287
    },
    {
      "step": 4,
      "train_loss": 0.023469221081425094,
      "train_quality": 0.30785259864685455,
      "val_loss": 0.0219526179585587,
      "val_quality": 0.3187118564585232,
      "reg_loss": 0.023579023069596437,
      "jitter": 0.001,
      "weight_norm_sq": 0.1098019881713432
    },
    {
      "step": 5,
      "train_loss": 0.023439661076800837,
      "train_quality": 0.3087243736543711,
      "val_loss": 0.021938500849679774,
      "val_quality": 0.3191499736306277,
      "reg_loss": 0.02355385028193929,
      "jitter": 0.001,
      "weight_norm_sq": 0.11418920513845293
    },
    {
      "step": 6,
      "train_loss": 0.023432547338342814,
      "train_quality": 0.3089341699475904,
      "val_loss": 0.021931229103720327,
      "val_quality": 0.31937564850523126,
      "reg_loss": 0.023548543158372244,
      "jitter": 0.001,
      "weight_norm_sq": 0.11599582002942874
    },
    {
      "step": 7,
      "train_loss": 0.023429913556808124,
      "train_quality": 0.30901184466200227,
      "val_loss": 0.02192814354983052,
      "val_quality": 0.3194714070742254,
      "reg_loss": 0.02354687858307696,
      "jitter": 0.001,
      "weight_norm_sq": 0.11696502626883407
    },
    {
      "step": 8,
      "train_loss": 0.023428576266124757,
      "train_quality": 0.3090512836475626,
      "val_loss": 0.021927008148959082,
      "val_quality": 0.31950664365299397,
      "reg_loss": 0.02354617670907384,
      "jitter": 0.001,
      "weight_norm_sq": 0.11760044294908135
    },
    {
      "step": 9,
      "train_loss": 0.023427768194096626,
      "train_quality": 0.3090751150713853,
      "val_loss": 0.021926670688191686,
      "val_quality": 0.31951711657336146,
      "reg_loss": 0.02354583874895605,
      "jitter": 0.001,
      "weight_norm_sq": 0.11807055485942367
    }
  ],
  "summary": {
    "run_id": "MPO2-L2-d4-init0.01-jit0.1-rf0.5-seed7",
    "seed": 7,
    "model": "MPO2",
    "grid_params": {
      "model": "MPO2",
      "L": 2,
      "bond_dim": 4,
      "jitter_start": 0.1,
      "reduction_factor": 0.5,
      "init_strength": 0.01
    },
    "train_loss": 0.023428576266124757,
    "train_quality": 0.3090512836475626,
    "val_loss": 0.021927008148959082,
    "val_quality": 0.31950664365299397,
    "test_loss": 0.019211506288889464,
    "test_quality": 0.3100526863098546,
    "success": true
  }
}