{
  "experiment_name": "ntn_obesity",
  "run_name": "MPO2_L3_d8_j5_s256",
  "config": {
    "output_site": 1,
    "init_strength": 0.01,
    "batch_size": 1024,
    "n_epochs": 15,
    "jitter_decay": 0.25,
    "adaptive_jitter": false,
    "patience": 4,
    "min_delta": 1e-06,
    "train_selection": true,
    "rank": 5,
    "seeds": [
      42,
      7,
      123,
      256,
      999
    ],
    "model": "MPO2",
    "L": 3,
    "bond_dim": 8,
    "jitter_start": 5.0
  },
  "hparams": {
    "seed": 256,
    "model": "MPO2",
    "dataset": "obesity",
    "n_parameters": 3120,
    "output_site": 1,
    "init_strength": 0.01,
    "batch_size": 1024,
    "n_epochs": 15,
    "jitter_decay": 0.25,
    "adaptive_jitter": false,
    "patience": 4,
    "min_delta": 1e-06,
    "train_selection": true,
    "rank": 5,
    "seeds": [
      42,
      7,
      123,
      256,
      999
    ],
    "L": 3,
    "bond_dim": 8,
    "jitter_start": 5.0
  },
  "metrics_log": [
    {
      "step": -1,
      "train_loss": 7678.6638694908925,
      "train_quality": -2013.8605112134212,
      "val_loss": 6910.344881739184,
      "val_quality": -1918.8820192125124
    },
    {
      "step": 0,
      "train_loss": 2.543909502467698,
      "train_quality": 0.33248506670697875,
      "val_loss": 2.556928271349575,
      "val_quality": 0.28961568538317406,
      "reg_loss": 3.0466851396381287,
      "jitter": 5.0,
      "weight_norm_sq": 0.1005551274340862
    },
    {
      "step": 1,
      "train_loss": 1.8181785039361085,
      "train_quality": 0.5229149065277617,
      "val_loss": 1.8416095301656101,
      "val_quality": 0.48835071419973675,
      "reg_loss": 2.173493024994328,
      "jitter": 1.25,
      "weight_norm_sq": 0.2842516168465758
    },
    {
      "step": 2,
      "train_loss": 1.1757893187159631,
      "train_quality": 0.6914760812489638,
      "val_loss": 1.3157979807140354,
      "val_quality": 0.6344354837101523,
      "reg_loss": 1.4145502759002526,
      "jitter": 0.3125,
      "weight_norm_sq": 0.7640350629897259
    },
    {
      "step": 3,
      "train_loss": 0.7773703998439825,
      "train_quality": 0.7960201217486453,
      "val_loss": 1.196027675879712,
      "val_quality": 0.6677109364729596,
      "reg_loss": 0.9228044570647006,
      "jitter": 0.078125,
      "weight_norm_sq": 1.8615559324251916
    },
    {
      "step": 4,
      "train_loss": 0.5176663930029154,
      "train_quality": 0.864165746675272,
      "val_loss": 1.0824440339973822,
      "val_quality": 0.6992675657669343,
      "reg_loss": 0.6064493982359583,
      "jitter": 0.01953125,
      "weight_norm_sq": 4.545689867931799
    },
    {
      "step": 5,
      "train_loss": 0.3494717976269241,
      "train_quality": 0.9082995509649854,
      "val_loss": 1.1942546681638375,
      "val_quality": 0.6682035263063018,
      "reg_loss": 0.400431695724193,
      "jitter": 0.0048828125,
      "weight_norm_sq": 10.436587130320678
    },
    {
      "step": 6,
      "train_loss": 0.2682079623351018,
      "train_quality": 0.9296229602849067,
      "val_loss": 1.6123376615663063,
      "val_quality": 0.5520486837755004,
      "reg_loss": 0.2976875428062773,
      "jitter": 0.001220703125,
      "weight_norm_sq": 24.14967232198698
    },
    {
      "step": 7,
      "train_loss": 0.25325716198148235,
      "train_quality": 0.9335460096272841,
      "val_loss": 1.7638032418213354,
      "val_quality": 0.509967420244116,
      "reg_loss": 0.281360414382629,
      "jitter": 0.001,
      "weight_norm_sq": 28.10325240114664
    },
    {
      "step": 8,
      "train_loss": 0.24661815043425683,
      "train_quality": 0.9352880681972838,
      "val_loss": 1.8182533483684504,
      "val_quality": 0.4948396976350381,
      "reg_loss": 0.27574603499338707,
      "jitter": 0.001,
      "weight_norm_sq": 29.127884559130216
    }
  ],
  "summary": {
    "run_id": "MPO2-L3-d8-jit5-seed256",
    "seed": 256,
    "model": "MPO2",
    "grid_params": {
      "model": "MPO2",
      "L": 3,
      "bond_dim": 8,
      "jitter_start": 5.0
    },
    "n_parameters": 3120,
    "train_loss": 0.5176663930029154,
    "train_quality": 0.864165746675272,
    "val_loss": 1.0824440339973822,
    "val_quality": 0.6992675657669343,
    "test_loss": 1.039723890141773,
    "test_quality": 0.7393193263561463,
    "success": true,
    "singular": false
  }
}