{
  "experiment_name": "ntn_realstate_lmpo2",
  "run_name": "LMPO2_L3_d8_j5_s999",
  "config": {
    "output_site": 1,
    "init_strength": 0.01,
    "reduction_factor": 0.3,
    "rank": 5,
    "batch_size": 1024,
    "n_epochs": 15,
    "jitter_decay": 0.25,
    "adaptive_jitter": false,
    "patience": 4,
    "min_delta": 1e-06,
    "train_selection": true,
    "seeds": [
      42,
      7,
      123,
      256,
      999
    ],
    "model": "LMPO2",
    "L": 3,
    "bond_dim": 8,
    "jitter_start": 5.0
  },
  "hparams": {
    "seed": 999,
    "model": "LMPO2",
    "dataset": "realstate",
    "n_parameters": 2800,
    "output_site": 1,
    "init_strength": 0.01,
    "reduction_factor": 0.3,
    "rank": 5,
    "batch_size": 1024,
    "n_epochs": 15,
    "jitter_decay": 0.25,
    "adaptive_jitter": false,
    "patience": 4,
    "min_delta": 1e-06,
    "train_selection": true,
    "seeds": [
      42,
      7,
      123,
      256,
      999
    ],
    "L": 3,
    "bond_dim": 8,
    "jitter_start": 5.0
  },
  "metrics_log": [
    {
      "step": -1,
      "train_loss": 1669.555659695192,
      "train_quality": -7.716617379737832,
      "val_loss": 1481.749176961634,
      "val_quality": -7.881624019913771
    },
    {
      "step": 0,
      "train_loss": 1199.2611295740107,
      "train_quality": -5.261247023532791,
      "val_loss": 1133.313439096911,
      "val_quality": -5.793095632699535,
      "reg_loss": 1341.110412601729,
      "jitter": 5.0,
      "weight_norm_sq": 28.36985660554364
    },
    {
      "step": 1,
      "train_loss": 956.6343647273437,
      "train_quality": -3.994511971621953,
      "val_loss": 988.7271658387399,
      "val_quality": -4.926443612583151,
      "reg_loss": 1127.5046699942493,
      "jitter": 1.25,
      "weight_norm_sq": 136.6962442135244
    },
    {
      "step": 2,
      "train_loss": 624.1704835638279,
      "train_quality": -2.2587444769257474,
      "val_loss": 657.90558708668,
      "val_quality": -2.9434947263384403,
      "reg_loss": 998.168743906331,
      "jitter": 0.3125,
      "weight_norm_sq": 1196.79443309601
    },
    {
      "step": 3,
      "train_loss": 562.6372309622387,
      "train_quality": -1.9374842566125574,
      "val_loss": 705.0322742065273,
      "val_quality": -3.225972707639478,
      "reg_loss": 707.5239343239783,
      "jitter": 0.078125,
      "weight_norm_sq": 1854.549803030267
    },
    {
      "step": 4,
      "train_loss": 515.0962872841895,
      "train_quality": -1.6892767688856267,
      "val_loss": 649.8443492455413,
      "val_quality": -2.895175560886358,
      "reg_loss": 562.8890551789684,
      "jitter": 0.01953125,
      "weight_norm_sq": 2446.9897162126767
    },
    {
      "step": 5,
      "train_loss": 463.8127050002526,
      "train_quality": -1.4215292625143863,
      "val_loss": 588.5944615073843,
      "val_quality": -2.528042929662145,
      "reg_loss": 493.77409863530215,
      "jitter": 0.0048828125,
      "weight_norm_sq": 6136.093416458145
    },
    {
      "step": 6,
      "train_loss": 460.4719674874379,
      "train_quality": -1.4040875375283144,
      "val_loss": 590.5403145015098,
      "val_quality": -2.5397063980551455,
      "reg_loss": 470.7827717876153,
      "jitter": 0.001220703125,
      "weight_norm_sq": 8446.610882705332
    },
    {
      "step": 7,
      "train_loss": 460.3898914523386,
      "train_quality": -1.403659025073607,
      "val_loss": 590.214072959175,
      "val_quality": -2.537750901967315,
      "reg_loss": 469.0026164544596,
      "jitter": 0.001,
      "weight_norm_sq": 8612.72500212101
    },
    {
      "step": 8,
      "train_loss": 460.376396806322,
      "train_quality": -1.403588570599497,
      "val_loss": 590.0845627089727,
      "val_quality": -2.5369746158273214,
      "reg_loss": 468.9973329904408,
      "jitter": 0.001,
      "weight_norm_sq": 8620.936184118784
    },
    {
      "step": 9,
      "train_loss": 460.3659600326884,
      "train_quality": -1.403534081034016,
      "val_loss": 589.9926009438258,
      "val_quality": -2.5364233957997073,
      "reg_loss": 468.9899637367749,
      "jitter": 0.001,
      "weight_norm_sq": 8624.003704086495
    }
  ],
  "summary": {
    "run_id": "LMPO2-L3-d8-jit5-rf0.3-seed999",
    "seed": 999,
    "model": "LMPO2",
    "grid_params": {
      "model": "LMPO2",
      "L": 3,
      "bond_dim": 8,
      "jitter_start": 5.0,
      "reduction_factor": 0.3
    },
    "n_parameters": 2800,
    "train_loss": 463.8127050002526,
    "train_quality": -1.4215292625143863,
    "val_loss": 588.5944615073843,
    "val_quality": -2.528042929662145,
    "test_loss": 818.6034258186985,
    "test_quality": -3.9088302021795833,
    "success": false,
    "singular": false
  }
}