{
  "run_id": "LMPO2TypeI_GTN-L4-d16-rf0.1-seed123",
  "seed": 123,
  "model": "LMPO2TypeI_GTN",
  "dataset": "bank",
  "task": "classification",
  "params": {
    "output_site": 1,
    "init_strength": 0.01,
    "reduction_factor": 0.1,
    "rank": 5,
    "batch_size": 64,
    "n_epochs": 1000,
    "patience": 40,
    "min_delta": 1e-08,
    "optimizer": "adamw",
    "seeds": [
      42,
      7,
      123,
      256,
      999
    ],
    "model": "LMPO2TypeI_GTN",
    "L": 4,
    "bond_dim": 16,
    "lr": 0.01
  },
  "n_parameters": 149695,
  "train_loss": 480.15047590316357,
  "train_quality": 0.8386576926722912,
  "val_loss": 456.11497748201674,
  "val_quality": 0.8972279563550575,
  "test_loss": 363.7862855780593,
  "test_quality": 0.8360365673842525,
  "best_epoch": 50,
  "stopped_early": true,
  "patience_counter": 40,
  "success": true
}